pyclaron/FlyCapture2.dll
pyclaron/FlyCapture2_C.dll
pyclaron/MTC.dll
pyclaron/MTInterfaceDotNet.dll
pyclaron/PGRFlyCapture.dll
pyclaron/__init__.py
pyclaron/_pyclaron.pyd
pyclaron/libiomp5md.dll
pyclaron-0.0.4.dist-info/LICENSE
pyclaron-0.0.4.dist-info/METADATA
pyclaron-0.0.4.dist-info/WHEEL
pyclaron-0.0.4.dist-info/top_level.txt
pyclaron-0.0.4.dist-info/RECORD
